Workbook
Name Slicer_Order_Status: #N/A
Name Slicer_Order_Status1: #N/A
Name Slicer_Payment_Method: #N/A
Name Slicer_Payment_Method1: #N/A

Sheet Raw Data
A1: Order ID | B1: Order Date | C1: Product Name | D1: Category | E1: Region | F1: Quantity | G1: Unit Price | H1: Cost Price | I1: Order Status | J1: Payment Method
A2: ORD54842 | B2: 45658 | C2: Study Table | D2: Furniture | E2: Central | F2: 7 | G2: 7199 | H2: 5000 | I2: Delivered | J2: Debit Card
A3: ORD71454 | B3: 01/03/2025 | C3: Cotton T-Shirt | D3: Fashion | E3: West | F3: 3 | G3: 799 | H3: 350 | I3: Delivered | J3: UPI
A4: ORD54222 | B4: Jan 3, 2025 | C4: Cotton T-Shirt | D4: Fashion | E4: SOUTH | F4: 7 | G4: 699 | H4: 350 | I4: Delivered | J4: Debit Card
A5: oRD62802 | B5: 04.01.2025 | C5: bluetooth Speaker | D5: electronics | E5: sOUTH | F5: 6 | G5: 3099 | H5: 1800 | I5: delivered | J5: net Banking
A6: ORD34937 | B6: 2025/01/05 | C6: Redmi Note 13 | D6: Electronics | E6: South | F6: 8 | G6: 15799 | H6: 13500 | I6: Cancelled | J6: UPI
A7: ord28301 | B7: 45666 | C7: water purifier | D7: appliances | E7: north | F7: 4 | G7: 8899 | H7: 7000 | I7: shipped | J7: credit card
A8: ORD61155 | B8: Jan 9, 2025 | C8: LED Desk Lamp | D8: Home Decor | E8: South | F8: 5 | G8: 899 | H8: 500 | I8: Delivered | J8: Net Banking
A9: ORD35926 | B9: 01/16/2025 | C9: Mixer Grinder | D9: Appliances | E9: north | F9: 4 | G9: 3299 | H9: 2500 | I9: Shipped | J9: UPI
A10: oRD30270 | B10: 16.01.2025 | C10: samsung Galaxy M14 | D10: electronics | E10: east | F10: 8 | G10: 12799 | H10: 10800 | I10: delivered | J10: credit card
A11: ORD47891 | B11: 45674 | C11: PRINTER PAPER | D11: STATIONERY | E11: SOUTH | F11: 1 | G11: 199 | H11: 180 | I11: SHIPPED | J11: DEBIT CARD
A12: 12100 | B12: 2025/01/18 | C12: Study Table | D12: Furniture | E12: North | F12: 4 | G12: 6999 | H12: 5000 | I12: Delivered | J12: UPI
A13: ORD43265 | B13: 45676 | C13: Cotton T-Shirt | D13: Fashion | E13: Central | F13: 2 | G13: 599 | H13: 350 | I13: Returned | J13: Debit Card
A14: ord99264 | B14: 45679 | C14: samsung galaxy m14 | D14: electronics | E14: central | F14: 5 | G14: 13099 | H14: Rs. 10,800 | I14: delivered | J14: upi
A15: oRD16441 | B15: 22.01.2025 | C15: coffee Mug | D15: home Decor | E15: north | F15: 10 | G15: 249 | H15: 90 | I15: delivered | J15: debit Card
A16: ORD54289 | B16: Jan 23, 2025 | C16: Bluetooth Speaker | D16: Electronics | E16: South | F16: 2 | G16: 2799 | H16: 1800 | I16: Returned | J16: Cash
A17: ORD52038 | B17: 45681 | C17: Study Table | D17: Furniture | E17: north | F17: 3 | G17: Rs. 7,099 | H17: 5000 | I17: Processing | J17: Cash
A18: ORD28779 | B18: 2025/01/26 | C18: Bluetooth Speaker | D18: Electronics | E18: North | F18: 2 | G18: 2899 | H18: 1,800 | I18: Cancelled | J18: Credit Card
A19: ORD10212 | B19: 45683 | C19: LED Desk Lamp | D19: Home Decor | E19: West | F19: 2 | G19: 699 | H19: 500 | I19: Cancelled | J19: Credit Card
A20: oRD50395 | B20: 27.01.2025 | C20: redmi Note 13 | D20: electronics | E20: north | F20: 2 | G20: 16099 | H20: 13500 | I20: delivered | J20: credit card
A21: ord15112 | B21: 01/30/2025 | C21: study table | D21: furniture | E21: north | F21: 8 | G21: 6,899 | H21: 5000 | I21: returned | J21: credit card
A22: ORD21323 | B22: 45689 | C22: COTTON T-SHIRT | D22: FASHION | E22: SOUTH | F22: 10 | G22: 699 | H22: 350 | I22: PROCESSING | J22: UPI
A23: ORD96827 | B23: 45690 | C23: Smart Watch | D23: Electronics | E23: North | F23: 7 | G23: 3699 | H23: 2400 | I23: Shipped | J23: Credit Card
A24: 48387 | B24: 2025/02/04 | C24: Printer Paper | D24: Stationery | E24: South | F24: 9 | G24: 499 | H24: 180 | I24: Shipped | J24: Cash
A25: oRD55831 | B25: 04.02.2025 | C25: smart Watch | D25: electronics | E25: west | F25: 7 | G25: 3599 | H25: 2400 | I25: delivered | J25: credit Card
A26: ORD84416 | B26: 45695 | C26: Mixer Grinder | D26: Appliances | E26: north | F26: 3 | G26: 3599 | H26: 2500 | I26: Delivered | J26: credit card
A27: ORD96518 | B27: 02/07/2025 | C27: Water Purifier | D27: Appliances | E27: South | F27: 6 | G27: 8899 | H27: 7000 | I27: Delivered | J27: UPI
A28: ord57901 | B28: Feb 7, 2025 | C28: led desk lamp | D28: home decor | E28: east | F28: 5 | G28: 799 | H28: 500 | I28: cancelled | J28: net banking
A29: ORD62046 | B29: 45696 | C29: Cotton T-Shirt | D29: Fashion | E29: Central | F29: 1 | G29: 599 | H29: 350 | I29: Delivered | J29: credit card
A30: oRD47012 | B30: 2025/02/08 | C30: samsung Galaxy M14 | D30: electronics | E30: north | F30: 3 | G30: 13199 | H30: 10800 | I30: delivered | J30: net Banking
A31: ORD97746 | B31: 45697 | C31: Coffee Mug | D31: Home Decor | E31: SOUTH | F31: 10 | G31: 349 | H31: 90 | I31: Processing | J31: upi
A32: ORD56775 | B32: Feb 10, 2025 | C32: Bluetooth Speaker | D32: Electronics | E32: Central | F32: 6 | G32: 3199 | H32: 1800 | I32: Cancelled | J32: Cash
A33: ORD59025 | B33: 02/11/2025 | C33: WATER PURIFIER | D33: APPLIANCES | E33: NORTH | F33: 3 | G33: 9199 | H33: Rs. 7,000 | I33: SHIPPED | J33: UPI
A34: ORD25349 | B34: 45700 | C34: LED Desk Lamp | D34: Home Decor | E34: North | F34: 2 | G34: 999 | H34: 500 | I34: Delivered | J34: UPI
A35: ORD25349 | B35: 45700 | C35: LED Desk Lamp | D35: Home Decor | E35: North | F35: 2 | G35: 999 | H35: 500 | I35: Delivered | J35: UPI
A36: ord93900 | B36: 14.02.2025 | C36: printer paper | D36: stationery | E36: south | F36: 3 | G36: 399 | H36: 180 | I36: returned | J36: upi
A37: 67364 | B37: 2025/02/15 | C37: Coffee Mug | D37: Home Decor | E37: Central | F37: 2 | G37: Rs. 149 | H37: 90 | I37: Delivered | J37: Credit Card
B38: 45704 | C38: Notebook Pack | D38: Stationery | E38: West | F38: 7 | G38: 99 | H38: 120 | I38: Returned | J38: Credit Card
A39: ORD61036 | B39: 45705 | C39: Study Table | D39: Furniture | E39: Central | F39: 7 | G39: 6799 | I39: Delivered | J39: credit card
A40: ORD76470 | B40: 02/18/2025 | C40: Redmi Note 13 | D40: Electronics | E40: north | F40: 7 | G40: 15999 | H40: 13500 | I40: Delivered | J40: Credit Card
A41: oRD22795 | B41: 18.02.2025 | C41: notebook Pack | D41: stationery | E41: north | F41: 8 | G41: 99 | H41: 120 | I41: delivered | J41: debit Card
A42: ORD62481 | B42: 45706 | C42: Smart Watch | D42: Electronics | F42: 7 | H42: 2,400 | I42: Returned | J42: upi
A43: ord88402 | B43: 2025/02/20 | C43: running shoes | D43: fashion | E43: west | F43: 8 | G43: 2699 | H43: 1400 | I43: shipped | J43: credit card
A44: ORD84873 | B44: 45709 | C44: Mixer Grinder | D44: Appliances | E44: SOUTH | G44: 3299 | H44: 2500 | I44: Shipped | J44: UPI
A45: ORD80002 | B45: Feb 24, 2025 | C45: SAMSUNG GALAXY M14 | D45: ELECTRONICS | E45: NORTH | F45: 1 | G45: 12,999 | H45: 10800 | I45: SHIPPED | J45: UPI
A46: oRD63545 | B46: 26.02.2025 | C46: water Purifier | D46: appliances | E46: east | F46: 5 | G46: 8999 | H46: 7000 | I46: shipped | J46: credit card
A47: ORD55853 | B47: 45719 | C47: Cotton T-Shirt | D47: Fashion | E47: West | F47: 10 | G47: 699 | H47: 350 | I47: Cancelled | J47: credit card
A48: ORD73372 | B48: 45720 | C48: Smart Watch | D48: Electronics | E48: North | F48: 5 | G48: 3599 | H48: 2400 | J48: Credit Card
A49: 39480 | B49: 2025/03/10 | C49: Running Shoes | D49: Fashion | E49: Central | F49: 3 | G49: 2299 | H49: 1400 | I49: Delivered | J49: UPI
A50: ord41424 | B50: 45729 | C50: water purifier | D50: appliances | E50: south | F50: 6 | G50: 8899 | H50: 7000 | I50: delivered | J50: credit card
A51: oRD69690 | B51: 13.03.2025 | C51: boat Headphones | D51: electronics | E51: east | F51: 2 | G51: 2199 | H51: 1200 | I51: delivered | J51: net Banking
A52: ORD90297 | B52: 03/14/2025 | C52: Coffee Mug | D52: Home Decor | E52: East | F52: 2 | G52: 49 | H52: 90 | I52: Delivered | J52: upi
A53: ORD52784 | B53: Mar 15, 2025 | C53: Study Table | D53: Furniture | E53: north | F53: 2 | G53: 7099 | H53: Rs. 5,000 | I53: Delivered | J53: upi
A54: ORD56636 | B54: 45732 | C54: Printer Paper | D54: Stationery | E54: West | F54: 1 | G54: 199 | H54: 180 | I54: Delivered
A55: ORD49698 | B55: 2025/03/17 | C55: Bluetooth Speaker | D55: Electronics | E55: East | F55: 6 | G55: 2999 | H55: 1800 | I55: Shipped | J55: Cash
A56: ORD53217 | B56: 18.03.2025 | C56: COFFEE MUG | D56: HOME DECOR | E56: NORTH | F56: 8 | G56: Rs. 249 | H56: 90 | I56: SHIPPED | J56: CREDIT CARD
A57: ord76515 | B57: Mar 19, 2025 | C57: office chair | D57: furniture | E57: south | F57: 3 | G57: 5399 | H57: 3800 | I57: delivered | J57: cash
A58: ORD92104 | B58: 03/20/2025 | C58: Study Table | D58: Furniture | E58: North | F58: 7 | G58: 6899 | H58: 5000 | I58: Shipped | J58: Net Banking
A59: ORD23649 | B59: 45737 | C59: LED Desk Lamp | D59: Home Decor | E59: East | F59: 5 | G59: 799 | H59: 500 | I59: Delivered | J59: Cash
A60: ORD55598 | B60: 45738 | C60: Study Table | D60: Furniture | E60: West | F60: 1 | G60: 7099 | H60: 5000 | I60: Delivered | J60: UPI
A61: 49033 | B61: 2025/03/22 | C61: smart Watch | D61: electronics | E61: north | F61: 9 | G61: 3499 | H61: 2400 | I61: delivered | J61: cash
A62: ORD50891 | B62: 45739 | C62: Boat Headphones | D62: Electronics | E62: South | F62: 10 | G62: 1899 | H62: 1200 | I62: Delivered | J62: Cash
A63: ORD63635 | B63: 45740 | C63: Coton T-Shirt | D63: Fashion | E63: Central | F63: 3 | G63: 799 | H63: 350 | I63: Cancelled | J63: Credit Card
A64: ord93804 | B64: 03/26/2025 | C64: led desk lamp | D64: home decor | E64: north | F64: 4 | G64: 799 | H64: 500 | I64: delivered | J64: net banking
A65: ORD15299 | B65: Mar 26, 2025 | C65: Coffee Mug | D65: Home Decor | E65: East | F65: 7 | G65: 149 | H65: 90 | I65: Cancelled | J65: upi
A66: oRD61295 | B66: 28.03.2025 | C66: water Purifier | D66: appliances | E66: north | F66: 3 | G66: 8999 | H66: 7000 | I66: returned | J66: net Banking
A67: ORD91365 | B67: 2025/03/28 | C67: OFFICE CHAIR | D67: FURNITURE | E67: NORTH | F67: 4 | G67: 5399 | H67: 3800 | I67: SHIPPED | J67: UPI
A68: ORD26498 | B68: 45745 | C68: Notebook Pack | D68: Stationery | E68: north | F68: 8 | G68: 299 | H68: 120 | I68: Returned | J68: UPI
A69: ORD92675 | B69: Apr 2, 2025 | C69: Bluetooth Speaker | D69: Electronics | E69: East | F69: 8 | G69: 3099 | H69: 1800 | I69: Cancelled | J69: Cash
A70: ORD92675 | B70: Apr 2, 2025 | C70: Bluetooth Speaker | D70: Electronics | E70: East | F70: 8 | G70: 3099 | H70: 1800 | I70: Cancelled | J70: Cash
A71: ORD29943 | B71: 04/02/2025 | C71: LED Desk Lamp | D71: Home Decor | E71: West | F71: 9 | G71: 699 | H71: 500 | I71: Processing | J71: upi
A72: ord88283 | B72: 05.04.2025 | C72: printer paper | D72: stationery | E72: north | F72: 5 | G72: 499 | H72: 180 | I72: shipped | J72: upi
A73: ORD46381 | B73: 45752 | C73: Boat Headphones | D73: Electronics | E73: West | F73: 1 | G73: 2099 | H73: Rs. 1,200 | I73: Delivered | J73: UPI
A74: 78254 | B74: 2025/04/06 | C74: Notebook Pack | D74: Stationery | E74: Central | F74: 10 | G74: 199 | H74: 120 | I74: Delivered | J74: credit card
A75: ORD65947 | B75: 45754 | C75: Printer Paper | D75: Stationery | E75: Central | F75: 10 | G75: 199 | H75: 180 | I75: Delivered | J75: credit card
B76: 45755 | C76: Mixer Grinder | D76: Appliances | E76: Central | F76: 9 | G76: Rs. 3,599 | H76: 2500 | I76: Processing | J76: Credit Card
A77: oRD24753 | B77: 10.04.2025 | C77: smart Watch | D77: electronics | E77: central | F77: 8 | G77: 3699 | H77: 2400 | I77: delivered | J77: debit Card
A78: ORD35906 | B78: Apr 10, 2025 | C78: Notebook Pack | D78: Stationery | E78: North | F78: 6 | G78: 299 | H78: 120 | I78: Delivered | J78: Debit Card
A79: ORD14067 | B79: 45758 | C79: COFFEE MUG | D79: HOME DECOR | E79: SOUTH | F79: 3 | G79: 449 | H79: 90 | I79: RETURNED | J79: CREDIT CARD
A80: ORD24674 | B80: 2025/04/11 | C80: Office Chair | D80: Furniture | E80: North | F80: 2 | G80: 5399 | H80: 3800 | I80: Delivered | J80: Net Banking
A81: ORD64247 | B81: 45758 | C81: Notebook Pack | D81: Stationery | E81: north | F81: 5 | G81: 199 | H81: 120 | I81: Processing | J81: Debit Card
A82: oRD97416 | B82: 13.04.2025 | C82: boat Headphones | D82: electronics | E82: east | F82: 1 | G82: 1799 | H82: 1200 | I82: delivered | J82: credit card
A83: ORD63858 | B83: 04/14/2025 | C83: Cotton T-Shirt | D83: Fashion | E83: north | F83: 5 | G83: 999 | I83: Delivered | J83: Credit Card
A84: ORD55966 | B84: 45761 | C84: Running Shoes | D84: Fashion | F84: 4 | G84: 2399 | H84: 1400 | I84: Cancelled | J84: Credit Card
A85: ORD27071 | B85: 45762 | C85: LED Desk Lamp | D85: Home Decor | E85: SOUTH | F85: 5 | G85: 899 | H85: 500 | I85: Delivered | J85: UPI
A86: 90598 | B86: 2025/04/16 | C86: water purifier | D86: appliances | E86: north | F86: 4 | H86: 7000 | I86: delivered | J86: upi
A87: oRD49794 | B87: 18.04.2025 | C87: coffee Mug | D87: home decor | E87: east | F87: 10 | G87: 349 | H87: 90 | I87: delivered | J87: credit Card
A88: ORD47011 | B88: 45766 | C88: Samsung Galaxy M14 | D88: Electronics | E88: north | G88: 12799 | H88: 10800 | I88: Delivered | J88: upi
A89: ORD28121 | B89: 04/23/2025 | C89: Office Chair | D89: Furniture | E89: South | F89: 5 | G89: 5499 | H89: 3,800 | I89: Cancelled | J89: Debit Card
A90: ORD49841 | B90: Apr 23, 2025 | C90: SMART WATCH | D90: ELECTRONICS | E90: WEST | F90: 8 | G90: 3599 | H90: 2400 | I90: DELIVERED | J90: CASH
A91: ORD26963 | B91: 45771 | C91: Mixer Grinder | D91: Appliances | E91: East | F91: 9 | G91: 3699 | H91: 2500 | I91: Returned | J91: upi
A92: oRD51923 | B92: 2025/04/24 | C92: office Chair | D92: furniture | E92: north | F92: 2 | G92: 5,299 | H92: Rs. 3,800 | I92: delivered | J92: cash
A93: ord41797 | B93: 45772 | C93: office chair | D93: furniture | E93: central | F93: 10 | G93: 5399 | H93: 3800 | I93: delivered | J93: cash
A94: ORD29161 | B94: Apr 25, 2025 | C94: Water Purifier | D94: Appliances | E94: East | F94: 5 | G94: 9099 | H94: 7000 | I94: Delivered | J94: Credit Card
A95: ORD53981 | B95: 04/29/2025 | C95: Samsung Galaxy M14 | D95: Electronics | E95: north | F95: 7 | G95: Rs. 12,799 | H95: 10800 | I95: Returned | J95: Debit Card
A96: ORD27844 | B96: 45776 | C96: Cotton T-Shirt | D96: Fashion | E96: SOUTH | F96: 5 | G96: 599 | H96: 350 | J96: Debit Card
A97: oRD31543 | B97: 30.04.2025 | C97: running Shoes | D97: fashion | E97: central | F97: 6 | G97: 2299 | H97: 1400 | I97: shipped | J97: credit card
A98: 78735 | B98: 2025/05/01 | C98: Printer Paper | D98: Stationery | E98: Central | F98: 4 | G98: 599 | H98: 180 | I98: Shipped | J98: UPI
A99: ORD68525 | B99: 45779 | C99: Office Chair | D99: Furniture | E99: South | F99: 7 | G99: 5499 | H99: 3800 | I99: Delivered | J99: Debit Card
A100: ord70536 | B100: 45780 | C100: smart watch | D100: electronics | E100: south | F100: 4 | G100: 3699 | H100: 2400 | I100: cancelled | J100: credit card
...

Sheet Data Cleaning
A1: Sales Data Cleaning & Transformation | O1: DATA QUALITY & METHODS
A2: Workflow: raw sales records cleaned, standardized, validated and converted into an interactive performance dashboard. | O2: Standardization | R2: Calculated Fields | U2: Validation | X2: Outcome
O3: Trimmed spaces, normalized case, standardized dates and converted currency text to numbers. | R3: Revenue, Profit and Profit Margin use structured table formulas for transparent recalculation. | U3: Used XLOOKUP cross-checks plus duplicate, missing-field and formula-error reviews. | X3: A reusable dataset connected to pivot tables, interactive slicers, charts and management insights.
A4: Records Cleaned | D4: Total Revenue | G4: Total Profit | J4: Overall Profit Margin
A5: =ROWS(Table1[Order ID]) -> 278 | D5: ="INR "&TEXT(SUM(Table1[Revenue]),"#,##0") -> INR 6,919,567 | G5: ="INR "&TEXT(SUM(Table1[Profit]),"#,##0") -> INR 1,732,187 | J5: =TEXT(IFERROR(SUM(Table1[Profit])/SUM(Table1[Revenue]),0),"0.0%") -> 25.0% | O5: Unique Orders | R5: Date Coverage | U5: Negative-Margin Orders | X5: Required-Field Completeness
O6: =ROWS(Table1[Order ID]) -> 278 | R6: =TEXT(MIN(Table1[Order Date]),"mmm yyyy")&" - "&TEXT(MAX(Table1[Order Date]),"mmm yyyy") -> Jan 2025 - Dec 2025 | U6: =COUNTIF(Table1[Profit Margin],"<0") -> 7 | X6: =TEXT(1-(COUNTBLANK(Table1[Order ID])+COUNTBLANK(Table1[Order Date])+COUNTBLANK(Table1[Product Name])+COUNTBLANK(Table1[Category])+COUNTBLANK(Table1[Region])+COUNTBLANK(Table1[Quantity])+COUNTBLANK(Table1[Unit Price])+COUNTBLANK(Table1[Cost Price])+COUNTBLANK(Table1[Order Status])+COUNTBLANK(Table1[Payment Method]))/(ROWS(Table1[Order ID])*10),"0%") -> 100%
A8: CLEANED DATASET | Standardized source fields and formula-driven business metrics | O8: XLOOKUP VALIDATION | Retrieve each cleaned record by Order ID and compare all transformed fields
A9: Order ID | B9: Order Date | C9: Product Name | D9: Category | E9: Region | F9: Quantity | G9: Unit Price | H9: Cost Price | I9: Order Status | J9: Payment Method | K9: Revenue | L9: Profit | M9: Profit Margin | O9: Order ID | P9: Order Date | Q9: Product Name | R9: Category | S9: Region | T9: Quantity | U9: Unit Price | V9: Cost Price | W9: Order Status | X9: Payment Method | Y9: Revenue | Z9: Profit | AA9: Profit Margin
A10: ORD54842 | B10: 45658 | C10: Study Table | D10: Furniture | E10: Central | F10: 7 | G10: 7199 | H10: 5000 | I10: Delivered | J10: Debit Card | K10: =Table1[[#This Row],[Quantity]]*Table1[[#This Row],[Unit Price]] -> 50393 | L10: =Table1[[#This Row],[Revenue]]-Table1[[#This Row],[Cost Price]]*Table1[[#This Row],[Quantity]] -> 15393 | M10: =IFERROR(Table1[[#This Row],[Profit]]/Table1[[#This Row],[Revenue]],"") -> 0.30545909 | O10: ORD54842 | P10: {=_xlfn.XLOOKUP(O10,Table1[Order ID],Table1[[Order Date]:[Profit Margin]],0,0,1)} -> 45658 | Q10: Study Table | R10: Furniture | S10: Central | T10: 7 | U10: 7199 | V10: 5000 | W10: Delivered | X10: Debit Card | Y10: 50393 | Z10: 15393 | AA10: 0.30545909
A11: ORD71454 | B11: 45660 | C11: Cotton T-Shirt | D11: Fashion | E11: West | F11: 3 | G11: 799 | H11: 350 | I11: Delivered | J11: UPI | K11: =Table1[[#This Row],[Quantity]]*Table1[[#This Row],[Unit Price]] -> 2397 | L11: =Table1[[#This Row],[Revenue]]-Table1[[#This Row],[Cost Price]]*Table1[[#This Row],[Quantity]] -> 1347 | M11: =IFERROR(Table1[[#This Row],[Profit]]/Table1[[#This Row],[Revenue]],"") -> 0.56195244 | O11: ORD71454 | P11: {=_xlfn.XLOOKUP(O11,Table1[Order ID],Table1[[Order Date]:[Profit Margin]],0,0,1)} -> 45660 | Q11: Cotton T-Shirt | R11: Fashion | S11: West | T11: 3 | U11: 799 | V11: 350 | W11: Delivered | X11: UPI | Y11: 2397 | Z11: 1347 | AA11: 0.56195244
A12: ORD54222 | B12: 45660 | C12: Cotton T-Shirt | D12: Fashion | E12: South | F12: 7 | G12: 699 | H12: 350 | I12: Delivered | J12: Debit Card | K12: =Table1[[#This Row],[Quantity]]*Table1[[#This Row],[Unit Price]] -> 4893 | L12: =Table1[[#This Row],[Revenue]]-Table1[[#This Row],[Cost Price]]*Table1[[#This Row],[Quantity]] -> 2443 | M12: =IFERROR(Table1[[#This Row],[Profit]]/Table1[[#This Row],[Revenue]],"") -> 0.49928469 | O12: ORD54222 | P12: {=_xlfn.XLOOKUP(O12,Table1[Order ID],Table1[[Order Date]:[Profit Margin]],0,0,1)} -> 45660 | Q12: Cotton T-Shirt | R12: Fashion | S12: South | T12: 7 | U12: 699 | V12: 350 | W12: Delivered | X12: Debit Card | Y12: 4893 | Z12: 2443 | AA12: 0.49928469
A13: ORD62802 | B13: 45661 | C13: Bluetooth Speaker | D13: Electronics | E13: South | F13: 6 | G13: 3099 | H13: 1800 | I13: Delivered | J13: Net Banking | K13: =Table1[[#This Row],[Quantity]]*Table1[[#This Row],[Unit Price]] -> 18594 | L13: =Table1[[#This Row],[Revenue]]-Table1[[#This Row],[Cost Price]]*Table1[[#This Row],[Quantity]] -> 7794 | M13: =IFERROR(Table1[[#This Row],[Profit]]/Table1[[#This Row],[Revenue]],"") -> 0.41916747 | O13: ORD62802 | P13: {=_xlfn.XLOOKUP(O13,Table1[Order ID],Table1[[Order Date]:[Profit Margin]],0,0,1)} -> 45661 | Q13: Bluetooth Speaker | R13: Electronics | S13: South | T13: 6 | U13: 3099 | V13: 1800 | W13: Delivered | X13: Net Banking | Y13: 18594 | Z13: 7794 | AA13: 0.41916747
A14: ORD34937 | B14: 45662 | C14: Redmi Note 13 | D14: Electronics | E14: South | F14: 8 | G14: 15799 | H14: 13500 | I14: Cancelled | J14: UPI | K14: =Table1[[#This Row],[Quantity]]*Table1[[#This Row],[Unit Price]] -> 126392 | L14: =Table1[[#This Row],[Revenue]]-Table1[[#This Row],[Cost Price]]*Table1[[#This Row],[Quantity]] -> 18392 | M14: =IFERROR(Table1[[#This Row],[Profit]]/Table1[[#This Row],[Revenue]],"") -> 0.14551554 | O14: ORD34937 | P14: {=_xlfn.XLOOKUP(O14,Table1[Order ID],Table1[[Order Date]:[Profit Margin]],0,0,1)} -> 45662 | Q14: Redmi Note 13 | R14: Electronics | S14: South | T14: 8 | U14: 15799 | V14: 13500 | W14: Cancelled | X14: UPI | Y14: 126392 | Z14: 18392 | AA14: 0.14551554
A15: ORD28301 | B15: 45666 | C15: Water Purifier | D15: Appliances | E15: North | F15: 4 | G15: 8899 | H15: 7000 | I15: Shipped | J15: Credit Card | K15: =Table1[[#This Row],[Quantity]]*Table1[[#This Row],[Unit Price]] -> 35596 | L15: =Table1[[#This Row],[Revenue]]-Table1[[#This Row],[Cost Price]]*Table1[[#This Row],[Quantity]] -> 7596 | M15: =IFERROR(Table1[[#This Row],[Profit]]/Table1[[#This Row],[Revenue]],"") -> 0.21339476 | O15: ORD28301 | P15: {=_xlfn.XLOOKUP(O15,Table1[Order ID],Table1[[Order Date]:[Profit Margin]],0,0,1)} -> 45666 | Q15: Water Purifier | R15: Appliances | S15: North | T15: 4 | U15: 8899 | V15: 7000 | W15: Shipped | X15: Credit Card | Y15: 35596 | Z15: 7596 | AA15: 0.21339476
A16: ORD61155 | B16: 45666 | C16: LED Desk Lamp | D16: Home Decor | E16: South | F16: 5 | G16: 899 | H16: 500 | I16: Delivered | J16: Net Banking | K16: =Table1[[#This Row],[Quantity]]*Table1[[#This Row],[Unit Price]] -> 4495 | L16: =Table1[[#This Row],[Revenue]]-Table1[[#This Row],[Cost Price]]*Table1[[#This Row],[Quantity]] -> 1995 | M16: =IFERROR(Table1[[#This Row],[Profit]]/Table1[[#This Row],[Revenue]],"") -> 0.44382647 | O16: ORD61155 | P16: {=_xlfn.XLOOKUP(O16,Table1[Order ID],Table1[[Order Date]:[Profit Margin]],0,0,1)} -> 45666 | Q16: LED Desk Lamp | R16: Home Decor | S16: South | T16: 5 | U16: 899 | V16: 500 | W16: Delivered | X16: Net Banking | Y16: 4495 | Z16: 1995 | AA16: 0.44382647
A17: ORD35926 | B17: 45673 | C17: Mixer Grinder | D17: Appliances | E17: North | F17: 4 | G17: 3299 | H17: 2500 | I17: Shipped | J17: UPI | K17: =Table1[[#This Row],[Quantity]]*Table1[[#This Row],[Unit Price]] -> 13196 | L17: =Table1[[#This Row],[Revenue]]-Table1[[#This Row],[Cost Price]]*Table1[[#This Row],[Quantity]] -> 3196 | M17: =IFERROR(Table1[[#This Row],[Profit]]/Table1[[#This Row],[Revenue]],"") -> 0.2421946 | O17: ORD35926 | P17: {=_xlfn.XLOOKUP(O17,Table1[Order ID],Table1[[Order Date]:[Profit Margin]],0,0,1)} -> 45673 | Q17: Mixer Grinder | R17: Appliances | S17: North | T17: 4 | U17: 3299 | V17: 2500 | W17: Shipped | X17: UPI | Y17: 13196 | Z17: 3196 | AA17: 0.2421946
A18: ORD30270 | B18: 45673 | C18: Samsung Galaxy M14 | D18: Electronics | E18: East | F18: 8 | G18: 12799 | H18: 10800 | I18: Delivered | J18: Credit Card | K18: =Table1[[#This Row],[Quantity]]*Table1[[#This Row],[Unit Price]] -> 102392 | L18: =Table1[[#This Row],[Revenue]]-Table1[[#This Row],[Cost Price]]*Table1[[#This Row],[Quantity]] -> 15992 | M18: =IFERROR(Table1[[#This Row],[Profit]]/Table1[[#This Row],[Revenue]],"") -> 0.15618408 | O18: ORD30270 | P18: {=_xlfn.XLOOKUP(O18,Table1[Order ID],Table1[[Order Date]:[Profit Margin]],0,0,1)} -> 45673 | Q18: Samsung Galaxy M14 | R18: Electronics | S18: East | T18: 8 | U18: 12799 | V18: 10800 | W18: Delivered | X18: Credit Card | Y18: 102392 | Z18: 15992 | AA18: 0.15618408
A19: ORD47891 | B19: 45674 | C19: Printer Paper | D19: Stationery | E19: South | F19: 1 | G19: 199 | H19: 180 | I19: Shipped | J19: Debit Card | K19: =Table1[[#This Row],[Quantity]]*Table1[[#This Row],[Unit Price]] -> 199 | L19: =Table1[[#This Row],[Revenue]]-Table1[[#This Row],[Cost Price]]*Table1[[#This Row],[Quantity]] -> 19 | M19: =IFERROR(Table1[[#This Row],[Profit]]/Table1[[#This Row],[Revenue]],"") -> 0.095477387 | O19: ORD47891 | P19: {=_xlfn.XLOOKUP(O19,Table1[Order ID],Table1[[Order Date]:[Profit Margin]],0,0,1)} -> 45674 | Q19: Printer Paper | R19: Stationery | S19: South | T19: 1 | U19: 199 | V19: 180 | W19: Shipped | X19: Debit Card | Y19: 199 | Z19: 19 | AA19: 0.095477387
A20: ORD12100 | B20: 45675 | C20: Study Table | D20: Furniture | E20: North | F20: 4 | G20: 6999 | H20: 5000 | I20: Delivered | J20: UPI | K20: =Table1[[#This Row],[Quantity]]*Table1[[#This Row],[Unit Price]] -> 27996 | L20: =Table1[[#This Row],[Revenue]]-Table1[[#This Row],[Cost Price]]*Table1[[#This Row],[Quantity]] -> 7996 | M20: =IFERROR(Table1[[#This Row],[Profit]]/Table1[[#This Row],[Revenue]],"") -> 0.28561223 | O20: ORD12100 | P20: {=_xlfn.XLOOKUP(O20,Table1[Order ID],Table1[[Order Date]:[Profit Margin]],0,0,1)} -> 45675 | Q20: Study Table | R20: Furniture | S20: North | T20: 4 | U20: 6999 | V20: 5000 | W20: Delivered | X20: UPI | Y20: 27996 | Z20: 7996 | AA20: 0.28561223
A21: ORD43265 | B21: 45676 | C21: Cotton T-Shirt | D21: Fashion | E21: Central | F21: 2 | G21: 599 | H21: 350 | I21: Returned | J21: Debit Card | K21: =Table1[[#This Row],[Quantity]]*Table1[[#This Row],[Unit Price]] -> 1198 | L21: =Table1[[#This Row],[Revenue]]-Table1[[#This Row],[Cost Price]]*Table1[[#This Row],[Quantity]] -> 498 | M21: =IFERROR(Table1[[#This Row],[Profit]]/Table1[[#This Row],[Revenue]],"") -> 0.41569282 | O21: ORD43265 | P21: {=_xlfn.XLOOKUP(O21,Table1[Order ID],Table1[[Order Date]:[Profit Margin]],0,0,1)} -> 45676 | Q21: Cotton T-Shirt | R21: Fashion | S21: Central | T21: 2 | U21: 599 | V21: 350 | W21: Returned | X21: Debit Card | Y21: 1198 | Z21: 498 | AA21: 0.41569282
... A287: ORD36719 | B287: 46020 | C287: Bluetooth Speaker | D287: Electronics | E287: North | F287: 10 | G287: 2899 | H287: 1800 | I287: Delivered | J287: Cash | K287: =Table1[[#This Row],[Quantity]]*Table1[[#This Row],[Unit Price]] -> 28990 | L287: =Table1[[#This Row],[Revenue]]-Table1[[#This Row],[Cost Price]]*Table1[[#This Row],[Quantity]] -> 10990 | M287: =IFERROR(Table1[[#This Row],[Profit]]/Table1[[#This Row],[Revenue]],"") -> 0.37909624 | O287: ORD36719 | P287: {=_xlfn.XLOOKUP(O287,Table1[Order ID],Table1[[Order Date]:[Profit Margin]],0,0,1)} -> 46020 | Q287: Bluetooth Speaker | R287: Electronics | S287: North | T287: 10 | U287: 2899 | V287: 1800 | W287: Delivered | X287: Cash | Y287: 28990 | Z287: 10990 | AA287: 0.37909624
A288: Totals | F288: =SUBTOTAL(109,Table1[Quantity]) -> 1533 | K288: =SUBTOTAL(109,Table1[Revenue]) -> 6919567 | L288: =SUBTOTAL(109,Table1[Profit]) -> 1732187 | M288: =IFERROR(L288/K288,"") -> 0.2503317 | P288: {=_xlfn.XLOOKUP(O288,Table1[Order ID],Table1[[Order Date]:[Profit Margin]],0,0,1)} -> 0

Sheet Sales Dashboard
A1: Sales Performance Dashboard
A4: Category Performance | H4: Regional Performance
A5: Row Labels | B5: Revenue (INR) | C5: Profit (INR) | D5: Avg Profit Margin | H5: Row Labels | I5: Revenue (INR) | J5: Profit (INR) | K5: Order Count
A6: Appliances | B6: 1487481 | C6: 345981 | D6: 0.24714808 | H6: Central | I6: 1103498 | J6: 298538 | K6: 47
A7: Electronics | B7: 3781585 | C7: 807385 | D7: 0.29185955 | H7: East | I7: 1001390 | J7: 271660 | K7: 43
A8: Fashion | B8: 323987 | C8: 151787 | D8: 0.47938655 | H8: North | I8: 1897406 | J8: 469016 | K8: 79
A9: Furniture | B9: 1153114 | C9: 339514 | D9: 0.29501903 | H9: South | I9: 2111436 | J9: 482246 | K9: 71
A10: Home Decor | B10: 111090 | C10: 53650 | D10: 0.40698969 | H10: West | I10: 805837 | J10: 210727 | K10: 38
A11: Stationery | B11: 62310 | C11: 33870 | D11: 0.42790812 | H11: Grand Total | I11: 6919567 | J11: 1732187 | K11: 278
A12: Grand Total | B12: 6919567 | C12: 1732187 | D12: 0.34392593
A14: Total Revenue | D14: Total Profit | G14: Average Margin | J14: Order Count | M14: INTERACTIVE FILTERS
A15: =B12 -> 6919567 | D15: =C12 -> 1732187 | G15: =D12 -> 0.34392593 | J15: =K11 -> 278
A43: PERFORMANCE INSIGHTS
A44: =IF($I$11=0,"1 | No regional data under the current filters.","1 | Regional leader: "&INDEX($H$6:$H$10,MATCH(MAX($I$6:$I$10),$I$6:$I$10,0))&" | Revenue INR "&TEXT(MAX($I$6:$I$10),"#,##0")&" | Profit INR "&TEXT(INDEX($J$6:$J$10,MATCH(MAX($I$6:$I$10),$I$6:$I$10,0)),"#,##0")) -> 1 | Regional leader: South | Revenue INR 2,111,436 | Profit INR 482,246
A45: =IF($B$12=0,"2 | No category data under the current Category slicer selections.","2 | Top category by revenue: "&INDEX($A$6:$A$11,MATCH(MAX($B$6:$B$11),$B$6:$B$11,0))&" | Revenue INR "&TEXT(MAX($B$6:$B$11),"#,##0")&" | Profit INR "&TEXT(INDEX($C$6:$C$11,MATCH(MAX($B$6:$B$11),$B$6:$B$11,0)),"#,##0")) -> 2 | Top category by revenue: Electronics | Revenue INR 3,781,585 | Profit INR 807,385
A46: =IF($B$12=0,"3 | Category margin insight unavailable because the current Category filters return no records.","3 | Highest average margin: "&INDEX($A$6:$A$11,MATCH(MAX($D$6:$D$11),$D$6:$D$11,0))&" at "&TEXT(MAX($D$6:$D$11),"0.0%")&" | Revenue INR "&TEXT(INDEX($B$6:$B$11,MATCH(MAX($D$6:$D$11),$D$6:$D$11,0)),"#,##0")) -> 3 | Highest average margin: Fashion at 47.9% | Revenue INR 323,987
A47: =IF($I$11=0,"4 | Regional insight unavailable because the current filters return no records.","4 | Lowest regional revenue: "&INDEX($H$6:$H$10,MATCH(MIN($I$6:$I$10),$I$6:$I$10,0))&" | INR "&TEXT(MIN($I$6:$I$10),"#,##0")&" | Review demand, assortment, and conversion") -> 4 | Lowest regional revenue: West | INR 805,837 | Review demand, assortment, and conversion
A48: =IF($I$11=0,"5 | Overall margin unavailable under the current filters.","5 | Overall profit margin: "&IFERROR(TEXT($J$11/$I$11,"0.0%"),"N/A")&" | Profit INR "&TEXT($J$11,"#,##0")&" on revenue INR "&TEXT($I$11,"#,##0")) -> 5 | Overall profit margin: 25.0% | Profit INR 1,732,187 on revenue INR 6,919,567

Sheet Chart Support
A1: Category | B1: Revenue | C1: Profit | E1: Region | F1: Revenue | G1: Profit
A2: =IF(OR('Sales Dashboard'!A6="",'Sales Dashboard'!A6="Grand Total"),"",'Sales Dashboard'!A6) -> Appliances | B2: =IF(A2="",NA(),'Sales Dashboard'!B6) -> 1487481 | C2: =IF(A2="",NA(),'Sales Dashboard'!C6) -> 345981 | E2: =IF(OR('Sales Dashboard'!H6="",'Sales Dashboard'!H6="Grand Total"),"",'Sales Dashboard'!H6) -> Central | F2: =IF(E2="",NA(),'Sales Dashboard'!I6) -> 1103498 | G2: =IF(E2="",NA(),'Sales Dashboard'!J6) -> 298538
A3: =IF(OR('Sales Dashboard'!A7="",'Sales Dashboard'!A7="Grand Total"),"",'Sales Dashboard'!A7) -> Electronics | B3: =IF(A3="",NA(),'Sales Dashboard'!B7) -> 3781585 | C3: =IF(A3="",NA(),'Sales Dashboard'!C7) -> 807385 | E3: =IF(OR('Sales Dashboard'!H7="",'Sales Dashboard'!H7="Grand Total"),"",'Sales Dashboard'!H7) -> East | F3: =IF(E3="",NA(),'Sales Dashboard'!I7) -> 1001390 | G3: =IF(E3="",NA(),'Sales Dashboard'!J7) -> 271660
A4: =IF(OR('Sales Dashboard'!A8="",'Sales Dashboard'!A8="Grand Total"),"",'Sales Dashboard'!A8) -> Fashion | B4: =IF(A4="",NA(),'Sales Dashboard'!B8) -> 323987 | C4: =IF(A4="",NA(),'Sales Dashboard'!C8) -> 151787 | E4: =IF(OR('Sales Dashboard'!H8="",'Sales Dashboard'!H8="Grand Total"),"",'Sales Dashboard'!H8) -> North | F4: =IF(E4="",NA(),'Sales Dashboard'!I8) -> 1897406 | G4: =IF(E4="",NA(),'Sales Dashboard'!J8) -> 469016
A5: =IF(OR('Sales Dashboard'!A9="",'Sales Dashboard'!A9="Grand Total"),"",'Sales Dashboard'!A9) -> Furniture | B5: =IF(A5="",NA(),'Sales Dashboard'!B9) -> 1153114 | C5: =IF(A5="",NA(),'Sales Dashboard'!C9) -> 339514 | E5: =IF(OR('Sales Dashboard'!H9="",'Sales Dashboard'!H9="Grand Total"),"",'Sales Dashboard'!H9) -> South | F5: =IF(E5="",NA(),'Sales Dashboard'!I9) -> 2111436 | G5: =IF(E5="",NA(),'Sales Dashboard'!J9) -> 482246
A6: =IF(OR('Sales Dashboard'!A10="",'Sales Dashboard'!A10="Grand Total"),"",'Sales Dashboard'!A10) -> Home Decor | B6: =IF(A6="",NA(),'Sales Dashboard'!B10) -> 111090 | C6: =IF(A6="",NA(),'Sales Dashboard'!C10) -> 53650 | E6: =IF(OR('Sales Dashboard'!H10="",'Sales Dashboard'!H10="Grand Total"),"",'Sales Dashboard'!H10) -> West | F6: =IF(E6="",NA(),'Sales Dashboard'!I10) -> 805837 | G6: =IF(E6="",NA(),'Sales Dashboard'!J10) -> 210727
A7: =IF(OR('Sales Dashboard'!A11="",'Sales Dashboard'!A11="Grand Total"),"",'Sales Dashboard'!A11) -> Stationery | B7: =IF(A7="",NA(),'Sales Dashboard'!B11) -> 62310 | C7: =IF(A7="",NA(),'Sales Dashboard'!C11) -> 33870
A10: Category | B10: Avg Margin % | E10: Region | F10: Order Count
A12: =IF(OR('Sales Dashboard'!A6="",'Sales Dashboard'!A6="Grand Total"),"",'Sales Dashboard'!A6) -> Appliances | B12: =IF(A12="",NA(),'Sales Dashboard'!D6) -> 0.24714808 | E12: =IF(OR('Sales Dashboard'!H6="",'Sales Dashboard'!H6="Grand Total"),"",'Sales Dashboard'!H6) -> Central | F12: =IF(E12="",NA(),'Sales Dashboard'!K6) -> 47
A13: =IF(OR('Sales Dashboard'!A7="",'Sales Dashboard'!A7="Grand Total"),"",'Sales Dashboard'!A7) -> Electronics | B13: =IF(A13="",NA(),'Sales Dashboard'!D7) -> 0.29185955 | E13: =IF(OR('Sales Dashboard'!H7="",'Sales Dashboard'!H7="Grand Total"),"",'Sales Dashboard'!H7) -> East | F13: =IF(E13="",NA(),'Sales Dashboard'!K7) -> 43
A14: =IF(OR('Sales Dashboard'!A8="",'Sales Dashboard'!A8="Grand Total"),"",'Sales Dashboard'!A8) -> Fashion | B14: =IF(A14="",NA(),'Sales Dashboard'!D8) -> 0.47938655 | E14: =IF(OR('Sales Dashboard'!H8="",'Sales Dashboard'!H8="Grand Total"),"",'Sales Dashboard'!H8) -> North | F14: =IF(E14="",NA(),'Sales Dashboard'!K8) -> 79
A15: =IF(OR('Sales Dashboard'!A9="",'Sales Dashboard'!A9="Grand Total"),"",'Sales Dashboard'!A9) -> Furniture | B15: =IF(A15="",NA(),'Sales Dashboard'!D9) -> 0.29501903 | E15: =IF(OR('Sales Dashboard'!H9="",'Sales Dashboard'!H9="Grand Total"),"",'Sales Dashboard'!H9) -> South | F15: =IF(E15="",NA(),'Sales Dashboard'!K9) -> 71
A16: =IF(OR('Sales Dashboard'!A10="",'Sales Dashboard'!A10="Grand Total"),"",'Sales Dashboard'!A10) -> Home Decor | B16: =IF(A16="",NA(),'Sales Dashboard'!D10) -> 0.40698969 | E16: =IF(OR('Sales Dashboard'!H10="",'Sales Dashboard'!H10="Grand Total"),"",'Sales Dashboard'!H10) -> West | F16: =IF(E16="",NA(),'Sales Dashboard'!K10) -> 38
A17: =IF(OR('Sales Dashboard'!A11="",'Sales Dashboard'!A11="Grand Total"),"",'Sales Dashboard'!A11) -> Stationery | B17: =IF(A17="",NA(),'Sales Dashboard'!D11) -> 0.42790812
